[
  {
    "bookImage": "https://wcfresource.a1edu.com/newsystem/image/dodoabc/cover/eb-pk-725.jpg",
    "title": "Aa",
    "vocaSrc": "",
    "passed": "Y",
    "passCount": 1,
    "bookCode": "eb-pk-301"
  },
  {
    "bookImage": "https://wcfresource.a1edu.com/newsystem/image/dodoabc/cover/eb-pk-726.jpg",
    "title": "Bb",
    "vocaSrc": "",
    "passed": "Y",
    "passCount": 1,
    "bookCode": "eb-pk-302"
  },
  {
    "bookImage": "https://wcfresource.a1edu.com/newsystem/image/dodoabc/cover/eb-pk-727.jpg",
    "title": "Bb",
    "vocaSrc": "",
    "passed": "Y",
    "passCount": 1,
    "bookCode": "eb-pk-302"
  },
  {
    "bookImage": "https://wcfresource.a1edu.com/newsystem/image/dodoabc/cover/eb-pk-728.jpg",
    "title": "Bb",
    "vocaSrc": "",
    "passed": "Y",
    "passCount": 1,
    "bookCode": "eb-pk-302"
  },
  {
    "bookImage": "https://wcfresource.a1edu.com/newsystem/image/dodoabc/cover/eb-pk-729.jpg",
    "title": "Bb",
    "vocaSrc": "",
    "passed": "Y",
    "passCount": 1,
    "bookCode": "eb-pk-302"
  },
  {
    "bookImage": "https://wcfresource.a1edu.com/newsystem/image/dodoabc/cover/eb-pk-730.jpg",
    "title": "Bb",
    "vocaSrc": "",
    "passed": "Y",
    "passCount": 1,
    "bookCode": "eb-pk-302"
  }
]